opengeode/AdaGenerator.py
opengeode/Asn1scc.py
opengeode/CGenerator.py
opengeode/Clipboard.py
opengeode/Connectors.py
opengeode/Helper.py
opengeode/Lander.py
opengeode/LlvmGenerator.py
opengeode/Pr.py
opengeode/QGenSDL.py
opengeode/Renderer.py
opengeode/Statechart.py
opengeode/StgBackend.py
opengeode/TextInteraction.py
opengeode/__init__.py
opengeode/genericSymbols.py
opengeode/icons.py
opengeode/ogAST.py
opengeode/ogParser.py
opengeode/opengeode.py
opengeode/sdl92Lexer.py
opengeode/sdl92Parser.py
opengeode/sdlSymbols.py
opengeode/undoCommands.py
opengeode_maxime1008-3.3.0.dist-info/LICENSE
opengeode_maxime1008-3.3.0.dist-info/METADATA
opengeode_maxime1008-3.3.0.dist-info/WHEEL
opengeode_maxime1008-3.3.0.dist-info/entry_points.txt
opengeode_maxime1008-3.3.0.dist-info/top_level.txt
opengeode_maxime1008-3.3.0.dist-info/RECORD
